Workbook

Sheet README
B2: RESTAURANT FINANCIAL MANAGEMENT MODEL
B3: A working financial system for food service operations — P&L, KPIs, cash flow, scenarios, and unit economics.
B5: About this model | C5: This is the financial infrastructure I designed and operated day to day while running food service businesses for 12 years. It covers the full cycle: transaction ledgers feeding a monthly P&L, a management dashboard with restaurant KPIs, daily cash position tracking, scenario forecasting, and menu-level pricing.
B7: Data disclaimer | C7: ALL FIGURES IN THIS WORKBOOK ARE ILLUSTRATIVE. They are sample values built to demonstrate the model's structure and logic, and do not represent the actual financial results of any business.
B9: Accounting approach | C9: Structured on accrual-basis principles: revenue and costs are recognized in the period they occur, with a separate cash-basis view for liquidity management. COGS is calculated from inventory movement (Beginning Inventory + Purchases - Ending Inventory), which isolates true consumption from purchase timing.
B11: How to read it | C11: BLUE text = manual input. BLACK text = formula. GREEN text = link to another sheet. Every calculated figure is a live formula — change an input and the model recalculates end to end.
B13: CONTENTS
B14: Executive Summary | C14: One-page business snapshot: headline metrics, value drivers, and risk factors.
B15: Controller Dashboard | C15: Management P&L by month with restaurant KPIs — food cost %, prime cost %, EBITDA margin.
B16: Monthly P&L | C16: Detailed monthly profit & loss by expense category, with net margin and capital accumulation.
B17: Cash Position | C17: Daily cash and receivables tracking across bank, cash, and payment processors.
B18: Scenario Forecast | C18: Six volume scenarios modeling revenue, staffing, cost structure, and resulting margin.
B19: Balance Sheet & Inventory | C19: Inventory movement, true COGS calculation, capital position, and customer revenue mix.
B20: Menu Pricing | C20: Item-level pricing by size with target margin and cost-driven price updates.
B22: CAPABILITIES DEMONSTRATED
B23: Month-end close structure · Balance sheet and bank reconciliation · Accounts payable tracking · Accrual-basis treatment · Multi-channel revenue recognition · Variance analysis · Cash flow forecasting · Inventory control and true COGS · Unit economics and pricing
B25: Built by Pablo Tidre · pablotidre@gmail.com · linkedin.com/in/pablo-tidre

Sheet Executive Summary
B2: SAMPLE PIZZERIA — BUSINESS SNAPSHOT
B3: Trailing 12 months · Illustrative figures · Owner-operated pizzeria with delivery
B5: KEY METRICS
B6: Operating Revenue (TTM) | D6: Adjusted EBITDA (TTM) | F6: Adj. EBITDA Margin | H6: Food Cost % | J6: Prime Cost % | L6: Avg Order Value
B7: =SUM('Controller Dashboard'!B9:M9) -> 425500 | D7: =SUM('Controller Dashboard'!B22:M22) -> 83125 | F7: =D7/B7 -> 0.1953584 | H7: =SUM('Controller Dashboard'!B12:M12)/B7 -> 0.31001175 | J7: =(SUM('Controller Dashboard'!B12:M12)+SUM('Controller Dashboard'!B14:M14))/B7 -> 0.49826087 | L7: 126
B10: VALUE DRIVERS
B11: 1. Recurring revenue base. Recurring customer share grew from ~3% to ~71% over 18 months. Predictable revenue is the core value driver — it earns a higher multiple than a business dependent on new-customer flow.
B12: 2. Strong cash generation. Adjusted EBITDA (before owner's draw) runs well above typical food service. Reported net income is lower by design: the owner's draw began mid-period, and prior profit was retained as working capital.
B13: 3. Revenue growth with rising ticket. Operating revenue grew ~3x while average order value rose ~16%, indicating growth came from genuine demand rather than discounting.
B15: RISK FACTORS
B16: • Acquisition ceiling. The total customer base has plateaued; recent growth comes from frequency and ticket size rather than new customers. The next phase requires a new acquisition lever or expanded delivery radius.
B17: • Margin discipline. With volume rising, the watch item is holding food cost and labor in check to protect the EBITDA margin. Prime cost is the metric to manage.
B19: BOTTOM LINE: A healthy operation with a real recurring base — the hard part solved. The constraint is the growth ceiling, not past performance. The next phase needs a new lever: ticket size or expansion.

Sheet Controller Dashboard
A1: MANAGEMENT P&L AND KPI DASHBOARD
A2: Trailing 12 months · Illustrative figures · Blue = input · Black = formula
A8: MANAGEMENT P&L | B8: Jan | C8: Feb | D8: Mar | E8: Apr | F8: May | G8: Jun | H8: Jul | I8: Aug | J8: Sep | K8: Oct | L8: Nov | M8: Dec | N8: TTM
A9: Operating Revenue | B9: 28500 | C9: 27800 | D9: 31200 | E9: 33500 | F9: 35800 | G9: 38200 | H9: 40500 | I9: 39100 | J9: 36400 | K9: 35200 | L9: 34800 | M9: 44500 | N9: =SUM(B9:M9) -> 425500
A10: Event Revenue (non-recurring) | B10: 0 | C10: 0 | D10: 0 | E10: 0 | F10: 0 | G10: 0 | H10: 0 | I10: 0 | J10: 0 | K10: 0 | L10: 0 | M10: 0 | N10: =SUM(B10:M10) -> 0
A11: Total Revenue | B11: =B9+B10 -> 28500 | C11: =C9+C10 -> 27800 | D11: =D9+D10 -> 31200 | E11: =E9+E10 -> 33500 | F11: =F9+F10 -> 35800 | G11: =G9+G10 -> 38200 | H11: =H9+H10 -> 40500 | I11: =I9+I10 -> 39100 | ... M11: =M9+M10 -> 44500 | N11: =SUM(B11:M11) -> 425500
A12: COGS / Food Cost | B12: 8840 | C12: 8620 | D12: 9670 | E12: 10380 | F12: 11100 | G12: 11840 | H12: 12560 | I12: 12120 | J12: 11280 | K12: 10910 | L12: 10790 | M12: 13800 | N12: =SUM(B12:M12) -> 131910
A13: Gross Profit | B13: =B11-B12 -> 19660 | C13: =C11-C12 -> 19180 | D13: =D11-D12 -> 21530 | E13: =E11-E12 -> 23120 | F13: =F11-F12 -> 24700 | G13: =G11-G12 -> 26360 | H13: =H11-H12 -> 27940 | I13: =I11-I12 -> 26980 | ... M13: =M11-M12 -> 30700 | N13: =SUM(B13:M13) -> 293590
A14: Staff Labor | B14: 5400 | C14: 5300 | D14: 5900 | E14: 6300 | F14: 6700 | G14: 7200 | H14: 7600 | I14: 7300 | J14: 6900 | K14: 6600 | L14: 6500 | M14: 8400 | N14: =SUM(B14:M14) -> 80100
A15: Owner's Draw | B15: 2800 | C15: 2800 | D15: 3000 | E15: 3200 | F15: 3200 | G15: 3400 | H15: 3600 | I15: 3400 | J15: 3200 | K15: 3200 | L15: 3200 | M15: 4000 | N15: =SUM(B15:M15) -> 39000
A16: Occupancy / Rent | B16: 3200 | C16: 3200 | D16: 3200 | E16: 3200 | F16: 3200 | G16: 3200 | H16: 3200 | I16: 3200 | J16: 3200 | K16: 3200 | L16: 3200 | M16: 3200 | N16: =SUM(B16:M16) -> 38400
A17: Utilities | B17: 950 | C17: 920 | D17: 1010 | E17: 1080 | F17: 1140 | G17: 1220 | H17: 1290 | I17: 1240 | J17: 1160 | K17: 1120 | L17: 1100 | M17: 1400 | N17: =SUM(B17:M17) -> 13630
A18: Marketing | B18: =B9*0.03 -> 855 | C18: =C9*0.03 -> 834 | D18: =D9*0.03 -> 936 | E18: =E9*0.03 -> 1005 | F18: =F9*0.03 -> 1074 | G18: =G9*0.03 -> 1146 | H18: =H9*0.03 -> 1215 | I18: =I9*0.03 -> 1173 | ... M18: =M9*0.03 -> 1335 | N18: =SUM(B18:M18) -> 12765
A19: Delivery / Logistics | B19: =B9*0.08 -> 2280 | C19: =C9*0.08 -> 2224 | D19: =D9*0.08 -> 2496 | E19: =E9*0.08 -> 2680 | F19: =F9*0.08 -> 2864 | G19: =G9*0.08 -> 3056 | H19: =H9*0.08 -> 3240 | I19: =I9*0.08 -> 3128 | ... M19: =M9*0.08 -> 3560 | N19: =SUM(B19:M19) -> 34040
A20: Other OpEx (G&A) | B20: 2200 | C20: 2150 | D20: 2350 | E20: 2500 | F20: 2650 | G20: 2800 | H20: 2950 | I20: 2850 | J20: 2700 | K20: 2600 | L20: 2580 | M20: 3200 | N20: =SUM(B20:M20) -> 31530
A21: Total OpEx (excl. owner's draw) | B21: =B14+B16+B17+B18+B19+B20 -> 14885 | C21: =C14+C16+C17+C18+C19+C20 -> 14628 | D21: =D14+D16+D17+D18+D19+D20 -> 15892 | E21: =E14+E16+E17+E18+E19+E20 -> 16765 | F21: =F14+F16+F17+F18+F19+F20 -> 17628 | G21: =G14+G16+G17+G18+G19+G20 -> 18622 | H21: =H14+H16+H17+H18+H19+H20 -> 19495 | I21: =I14+I16+I17+I18+I19+I20 -> 18891 | ... M21: =M14+M16+M17+M18+M19+M20 -> 21095 | N21: =SUM(B21:M21) -> 210465
A22: Adjusted EBITDA (pre owner's draw) | B22: =B13-B21 -> 4775 | C22: =C13-C21 -> 4552 | D22: =D13-D21 -> 5638 | E22: =E13-E21 -> 6355 | F22: =F13-F21 -> 7072 | G22: =G13-G21 -> 7738 | H22: =H13-H21 -> 8445 | I22: =I13-I21 -> 8089 | ... M22: =M13-M21 -> 9605 | N22: =SUM(B22:M22) -> 83125
A23: EBITDA (after owner's draw) | B23: =B22-B15 -> 1975 | C23: =C22-C15 -> 1752 | D23: =D22-D15 -> 2638 | E23: =E22-E15 -> 3155 | F23: =F22-F15 -> 3872 | G23: =G22-G15 -> 4338 | H23: =H22-H15 -> 4845 | I23: =I22-I15 -> 4689 | ... M23: =M22-M15 -> 5605 | N23: =SUM(B23:M23) -> 44125
A24: Taxes & Fees | B24: =B9*0.075 -> 2137.5 | C24: =C9*0.075 -> 2085 | D24: =D9*0.075 -> 2340 | E24: =E9*0.075 -> 2512.5 | F24: =F9*0.075 -> 2685 | G24: =G9*0.075 -> 2865 | H24: =H9*0.075 -> 3037.5 | I24: =I9*0.075 -> 2932.5 | ... M24: =M9*0.075 -> 3337.5 | N24: =SUM(B24:M24) -> 31912.5
A25: Net Income | B25: =B23-B24 -> -162.5 | C25: =C23-C24 -> -333 | D25: =D23-D24 -> 298 | E25: =E23-E24 -> 642.5 | F25: =F23-F24 -> 1187 | G25: =G23-G24 -> 1473 | H25: =H23-H24 -> 1807.5 | I25: =I23-I24 -> 1756.5 | ... M25: =M23-M24 -> 2267.5 | N25: =SUM(B25:M25) -> 12212.5
A27: KEY RESTAURANT KPIs (% of Operating Revenue)
A28: Food Cost % | B28: =B12/B9 -> 0.31017544 | C28: =C12/C9 -> 0.31007194 | D28: =D12/D9 -> 0.3099359 | E28: =E12/E9 -> 0.30985075 | F28: =F12/F9 -> 0.31005587 | G28: =G12/G9 -> 0.30994764 | H28: =H12/H9 -> 0.31012346 | I28: =I12/I9 -> 0.30997442 | ... N28: =N12/N9 -> 0.31001175
A29: Staff Labor % | B29: =B14/B9 -> 0.18947368 | C29: =C14/C9 -> 0.19064748 | D29: =D14/D9 -> 0.18910256 | E29: =E14/E9 -> 0.1880597 | F29: =F14/F9 -> 0.18715084 | G29: =G14/G9 -> 0.18848168 | H29: =H14/H9 -> 0.18765432 | I29: =I14/I9 -> 0.18670077 | ... N29: =N14/N9 -> 0.18824912
A30: Prime Cost % (Food + Labor) | B30: =(B12+B14)/B9 -> 0.49964912 | C30: =(C12+C14)/C9 -> 0.50071942 | D30: =(D12+D14)/D9 -> 0.49903846 | E30: =(E12+E14)/E9 -> 0.49791045 | F30: =(F12+F14)/F9 -> 0.4972067 | G30: =(G12+G14)/G9 -> 0.49842932 | H30: =(H12+H14)/H9 -> 0.49777778 | I30: =(I12+I14)/I9 -> 0.49667519 | ... N30: =(N12+N14)/N9 -> 0.49826087
A31: Gross Margin % | B31: =B13/B9 -> 0.68982456 | C31: =C13/C9 -> 0.68992806 | D31: =D13/D9 -> 0.6900641 | E31: =E13/E9 -> 0.69014925 | F31: =F13/F9 -> 0.68994413 | G31: =G13/G9 -> 0.69005236 | H31: =H13/H9 -> 0.68987654 | I31: =I13/I9 -> 0.69002558 | ... N31: =N13/N9 -> 0.68998825
A32: Adjusted EBITDA Margin % | B32: =B22/B9 -> 0.16754386 | C32: =C22/C9 -> 0.16374101 | D32: =D22/D9 -> 0.18070513 | E32: =E22/E9 -> 0.18970149 | F32: =F22/F9 -> 0.1975419 | G32: =G22/G9 -> 0.20256545 | H32: =H22/H9 -> 0.20851852 | I32: =I22/I9 -> 0.2068798 | ... N32: =N22/N9 -> 0.1953584
A33: Net Margin % | B33: =B25/B9 -> -0.0057017544 | C33: =C25/C9 -> -0.011978417 | D33: =D25/D9 -> 0.0095512821 | E33: =E25/E9 -> 0.019179104 | F33: =F25/F9 -> 0.033156425 | G33: =G25/G9 -> 0.038560209 | H33: =H25/H9 -> 0.04462963 | I33: =I25/I9 -> 0.044923274 | ... N33: =N25/N9 -> 0.028701528
A34: Owner's Draw % of Revenue | B34: =B15/B9 -> 0.098245614 | C34: =C15/C9 -> 0.10071942 | D34: =D15/D9 -> 0.096153846 | E34: =E15/E9 -> 0.095522388 | F34: =F15/F9 -> 0.089385475 | G34: =G15/G9 -> 0.089005236 | H34: =H15/H9 -> 0.088888889 | I34: =I15/I9 -> 0.086956522 | ... N34: =N15/N9 -> 0.091656874
A37: Chart source data
A38: Month | B38: Jan | C38: Feb | D38: Mar | E38: Apr | F38: May | G38: Jun | H38: Jul | I38: Aug | J38: Sep | K38: Oct | L38: Nov | M38: Dec
A39: Operating Revenue | B39: =B9 -> 28500 | C39: =C9 -> 27800 | D39: =D9 -> 31200 | E39: =E9 -> 33500 | F39: =F9 -> 35800 | G39: =G9 -> 38200 | H39: =H9 -> 40500 | I39: =I9 -> 39100 | ... M39: =M9 -> 44500
A40: Adjusted EBITDA | B40: =B22 -> 4775 | C40: =C22 -> 4552 | D40: =D22 -> 5638 | E40: =E22 -> 6355 | F40: =F22 -> 7072 | G40: =G22 -> 7738 | H40: =H22 -> 8445 | I40: =I22 -> 8089 | ... M40: =M22 -> 9605

Sheet Monthly P&L
A1: MONTHLY PROFIT & LOSS
A2: Detailed expense breakdown · Illustrative figures · Green = linked from Controller Dashboard
B4: Jan | C4: Feb | D4: Mar | E4: Apr | F4: May | G4: Jun | H4: Jul | I4: Aug | J4: Sep | K4: Oct | L4: Nov | M4: Dec | N4: TOTAL
A5: REVENUE
A6: Restaurant Sales | B6: ='Controller Dashboard'!B9 -> 28500 | C6: ='Controller Dashboard'!C9 -> 27800 | D6: ='Controller Dashboard'!D9 -> 31200 | E6: ='Controller Dashboard'!E9 -> 33500 | F6: ='Controller Dashboard'!F9 -> 35800 | G6: ='Controller Dashboard'!G9 -> 38200 | H6: ='Controller Dashboard'!H9 -> 40500 | I6: ='Controller Dashboard'!I9 -> 39100 | ... M6: ='Controller Dashboard'!M9 -> 44500 | N6: =SUM(B6:M6) -> 425500
A7: Event Revenue | B7: 0 | C7: 0 | D7: 0 | E7: 0 | F7: 0 | G7: 0 | H7: 0 | I7: 0 | J7: 0 | K7: 0 | L7: 0 | M7: 0 | N7: =SUM(B7:M7) -> 0
A8: Total Revenue | B8: =B6+B7 -> 28500 | C8: =C6+C7 -> 27800 | D8: =D6+D7 -> 31200 | E8: =E6+E7 -> 33500 | F8: =F6+F7 -> 35800 | G8: =G6+G7 -> 38200 | H8: =H6+H7 -> 40500 | I8: =I6+I7 -> 39100 | ... M8: =M6+M7 -> 44500 | N8: =SUM(B8:M8) -> 425500
A9: Sales Taxes | B9: =B8*0.065 -> 1852.5 | C9: =C8*0.065 -> 1807 | D9: =D8*0.065 -> 2028 | E9: =E8*0.065 -> 2177.5 | F9: =F8*0.065 -> 2327 | G9: =G8*0.065 -> 2483 | H9: =H8*0.065 -> 2632.5 | I9: =I8*0.065 -> 2541.5 | ... M9: =M8*0.065 -> 2892.5 | N9: =SUM(B9:M9) -> 27657.5
A10: Platform & Card Fees | B10: =B8*0.03 -> 855 | C10: =C8*0.03 -> 834 | D10: =D8*0.03 -> 936 | E10: =E8*0.03 -> 1005 | F10: =F8*0.03 -> 1074 | G10: =G8*0.03 -> 1146 | H10: =H8*0.03 -> 1215 | I10: =I8*0.03 -> 1173 | ... M10: =M8*0.03 -> 1335 | N10: =SUM(B10:M10) -> 12765
A11: Net Operating Revenue | B11: =B8-B9-B10 -> 25792.5 | C11: =C8-C9-C10 -> 25159 | D11: =D8-D9-D10 -> 28236 | E11: =E8-E9-E10 -> 30317.5 | F11: =F8-F9-F10 -> 32399 | G11: =G8-G9-G10 -> 34571 | H11: =H8-H9-H10 -> 36652.5 | I11: =I8-I9-I10 -> 35385.5 | ... M11: =M8-M9-M10 -> 40272.5 | N11: =SUM(B11:M11) -> 385077.5
A13: OPERATING EXPENSES
A14: Raw Materials (Food) | B14: ='Controller Dashboard'!B12 -> 8840 | C14: ='Controller Dashboard'!C12 -> 8620 | D14: ='Controller Dashboard'!D12 -> 9670 | E14: ='Controller Dashboard'!E12 -> 10380 | F14: ='Controller Dashboard'!F12 -> 11100 | G14: ='Controller Dashboard'!G12 -> 11840 | H14: ='Controller Dashboard'!H12 -> 12560 | I14: ='Controller Dashboard'!I12 -> 12120 | ... M14: ='Controller Dashboard'!M12 -> 13800 | N14: =SUM(B14:M14) -> 131910
A15: Payroll & Staff | B15: ='Controller Dashboard'!B14 -> 5400 | C15: ='Controller Dashboard'!C14 -> 5300 | D15: ='Controller Dashboard'!D14 -> 5900 | E15: ='Controller Dashboard'!E14 -> 6300 | F15: ='Controller Dashboard'!F14 -> 6700 | G15: ='Controller Dashboard'!G14 -> 7200 | H15: ='Controller Dashboard'!H14 -> 7600 | I15: ='Controller Dashboard'!I14 -> 7300 | ... M15: ='Controller Dashboard'!M14 -> 8400 | N15: =SUM(B15:M15) -> 80100
A16: Rent | B16: ='Controller Dashboard'!B16 -> 3200 | C16: ='Controller Dashboard'!C16 -> 3200 | D16: ='Controller Dashboard'!D16 -> 3200 | E16: ='Controller Dashboard'!E16 -> 3200 | F16: ='Controller Dashboard'!F16 -> 3200 | G16: ='Controller Dashboard'!G16 -> 3200 | H16: ='Controller Dashboard'!H16 -> 3200 | I16: ='Controller Dashboard'!I16 -> 3200 | ... M16: ='Controller Dashboard'!M16 -> 3200 | N16: =SUM(B16:M16) -> 38400
A17: Utilities (Power & Water) | B17: ='Controller Dashboard'!B17 -> 950 | C17: ='Controller Dashboard'!C17 -> 920 | D17: ='Controller Dashboard'!D17 -> 1010 | E17: ='Controller Dashboard'!E17 -> 1080 | F17: ='Controller Dashboard'!F17 -> 1140 | G17: ='Controller Dashboard'!G17 -> 1220 | H17: ='Controller Dashboard'!H17 -> 1290 | I17: ='Controller Dashboard'!I17 -> 1240 | ... M17: ='Controller Dashboard'!M17 -> 1400 | N17: =SUM(B17:M17) -> 13630
A18: Delivery / Motorbikes | B18: ='Controller Dashboard'!B19 -> 2280 | C18: ='Controller Dashboard'!C19 -> 2224 | D18: ='Controller Dashboard'!D19 -> 2496 | E18: ='Controller Dashboard'!E19 -> 2680 | F18: ='Controller Dashboard'!F19 -> 2864 | G18: ='Controller Dashboard'!G19 -> 3056 | H18: ='Controller Dashboard'!H19 -> 3240 | I18: ='Controller Dashboard'!I19 -> 3128 | ... M18: ='Controller Dashboard'!M19 -> 3560 | N18: =SUM(B18:M18) -> 34040
A19: Marketing | B19: ='Controller Dashboard'!B18 -> 855 | C19: ='Controller Dashboard'!C18 -> 834 | D19: ='Controller Dashboard'!D18 -> 936 | E19: ='Controller Dashboard'!E18 -> 1005 | F19: ='Controller Dashboard'!F18 -> 1074 | G19: ='Controller Dashboard'!G18 -> 1146 | H19: ='Controller Dashboard'!H18 -> 1215 | I19: ='Controller Dashboard'!I18 -> 1173 | ... M19: ='Controller Dashboard'!M18 -> 1335 | N19: =SUM(B19:M19) -> 12765
A20: Phone & Internet | B20: 160 | C20: 160 | D20: 160 | E20: 160 | F20: 160 | G20: 160 | H20: 160 | I20: 160 | J20: 160 | K20: 160 | L20: 160 | M20: 160 | N20: =SUM(B20:M20) -> 1920
A21: Accounting Services | B21: 550 | C21: 550 | D21: 550 | E21: 550 | F21: 550 | G21: 550 | H21: 550 | I21: 550 | J21: 550 | K21: 550 | L21: 550 | M21: 550 | N21: =SUM(B21:M21) -> 6600
A22: Insurance | B22: 180 | C22: 180 | D22: 180 | E22: 180 | F22: 180 | G22: 180 | H22: 180 | I22: 180 | J22: 180 | K22: 180 | L22: 180 | M22: 180 | N22: =SUM(B22:M22) -> 2160
A23: Security | B23: 200 | C23: 200 | D23: 200 | E23: 200 | F23: 200 | G23: 200 | H23: 200 | I23: 200 | J23: 200 | K23: 200 | L23: 200 | M23: 200 | N23: =SUM(B23:M23) -> 2400
A24: Software & Systems | B24: 250 | C24: 250 | D24: 250 | E24: 250 | F24: 250 | G24: 250 | H24: 250 | I24: 250 | J24: 250 | K24: 250 | L24: 250 | M24: 250 | N24: =SUM(B24:M24) -> 3000
A25: Legal | B25: 150 | C25: 150 | D25: 150 | E25: 150 | F25: 150 | G25: 150 | H25: 150 | I25: 150 | J25: 150 | K25: 150 | L25: 150 | M25: 150 | N25: =SUM(B25:M25) -> 1800
A26: Cleaning Supplies | B26: 250 | C26: 250 | D26: 250 | E26: 250 | F26: 250 | G26: 250 | H26: 250 | I26: 250 | J26: 250 | K26: 250 | L26: 250 | M26: 250 | N26: =SUM(B26:M26) -> 3000
A27: Maintenance | B27: 350 | C27: 350 | D27: 350 | E27: 350 | F27: 350 | G27: 350 | H27: 350 | I27: 350 | J27: 350 | K27: 350 | L27: 350 | M27: 350 | N27: =SUM(B27:M27) -> 4200
A28: Total Operating Expenses | B28: =SUM(B14:B27) -> 23615 | C28: =SUM(C14:C27) -> 23188 | D28: =SUM(D14:D27) -> 25302 | E28: =SUM(E14:E27) -> 26735 | F28: =SUM(F14:F27) -> 28168 | G28: =SUM(G14:G27) -> 29752 | H28: =SUM(H14:H27) -> 31195 | I28: =SUM(I14:I27) -> 30251 | ... M28: =SUM(M14:M27) -> 33785 | N28: =SUM(B28:M28) -> 335925
A30: Owner's Draw | B30: ='Controller Dashboard'!B15 -> 2800 | C30: ='Controller Dashboard'!C15 -> 2800 | D30: ='Controller Dashboard'!D15 -> 3000 | E30: ='Controller Dashboard'!E15 -> 3200 | F30: ='Controller Dashboard'!F15 -> 3200 | G30: ='Controller Dashboard'!G15 -> 3400 | H30: ='Controller Dashboard'!H15 -> 3600 | I30: ='Controller Dashboard'!I15 -> 3400 | ... M30: ='Controller Dashboard'!M15 -> 4000 | N30: =SUM(B30:M30) -> 39000
A31: Reinvestment | B31: 300 | C31: 300 | D31: 300 | E31: 300 | F31: 300 | G31: 300 | H31: 300 | I31: 300 | J31: 300 | K31: 300 | L31: 300 | M31: 300 | N31: =SUM(B31:M31) -> 3600
A33: NET PROFIT | B33: =B11-B28-B30-B31 -> -922.5 | C33: =C11-C28-C30-C31 -> -1129 | D33: =D11-D28-D30-D31 -> -366 | E33: =E11-E28-E30-E31 -> 82.5 | F33: =F11-F28-F30-F31 -> 731 | G33: =G11-G28-G30-G31 -> 1119 | H33: =H11-H28-H30-H31 -> 1557.5 | I33: =I11-I28-I30-I31 -> 1434.5 | ... M33: =M11-M28-M30-M31 -> 2187.5 | N33: =SUM(B33:M33) -> 6552.5
A34: Net Margin % | B34: =B33/B8 -> -0.032368421 | C34: =C33/C8 -> -0.040611511 | D34: =D33/D8 -> -0.011730769 | E34: =E33/E8 -> 0.0024626866 | F34: =F33/F8 -> 0.020418994 | G34: =G33/G8 -> 0.029293194 | H34: =H33/H8 -> 0.03845679 | I34: =I33/I8 -> 0.03668798 | ... N34: =N33/N8 -> 0.01539953
A35: Total Owner Benefit (profit + draw + reinvestment) | B35: =B33+B30+B31 -> 2177.5 | C35: =C33+C30+C31 -> 1971 | D35: =D33+D30+D31 -> 2934 | E35: =E33+E30+E31 -> 3582.5 | F35: =F33+F30+F31 -> 4231 | G35: =G33+G30+G31 -> 4819 | H35: =H33+H30+H31 -> 5457.5 | I35: =I33+I30+I31 -> 5134.5 | ... M35: =M33+M30+M31 -> 6487.5 | N35: =SUM(B35:M35) -> 49152.5

Sheet Cash Position
A1: DAILY CASH POSITION
A2: Liquidity tracking across bank, cash on hand, and payment-processor receivables · Illustrative figures
A4: Date | B4: Bank Balance | C4: Cash on Hand | D4: Processor Receivable | E4: Delivery Receivable | F4: Total Liquidity | G4: Paid Month-to-Date | H4: Scheduled Payables | I4: Projected Balance | J4: Coverage Ratio
A5: 2026-06-01 | B5: 32570 | C5: 400 | D5: 21760 | E5: 4030 | F5: =SUM(B5:E5) -> 58760 | G5: 19840 | H5: 54630 | I5: =F5-H5 -> 4130 | J5: =F5/H5 -> 1.0755995
A6: 2026-06-03 | B6: 34940 | C6: 400 | D6: 21290 | E6: 4030 | F6: =SUM(B6:E6) -> 60660 | G6: 21270 | H6: 53210 | I6: =F6-H6 -> 7450 | J6: =F6/H6 -> 1.1400113
A7: 2026-06-05 | B7: 34980 | C7: 300 | D7: 19880 | E7: 4030 | F7: =SUM(B7:E7) -> 59190 | G7: 23310 | H7: 51160 | I7: =F7-H7 -> 8030 | J7: =F7/H7 -> 1.1569586
A8: 2026-06-08 | B8: 27140 | C8: 300 | D8: 16630 | E8: 4030 | F8: =SUM(B8:E8) -> 48100 | G8: 26850 | H8: 47630 | I8: =F8-H8 -> 470 | J8: =F8/H8 -> 1.0098677
A9: 2026-06-10 | B9: 27890 | C9: 300 | D9: 15450 | E9: 4030 | F9: =SUM(B9:E9) -> 47670 | G9: 39330 | H9: 35140 | I9: =F9-H9 -> 12530 | J9: =F9/H9 -> 1.3565737
A10: 2026-06-12 | B10: 25820 | C10: 300 | D10: 14040 | E10: 4030 | F10: =SUM(B10:E10) -> 44190 | G10: 43190 | H10: 31280 | I10: =F10-H10 -> 12910 | J10: =F10/H10 -> 1.4127238
A11: 2026-06-15 | B11: 24930 | C11: 300 | D11: 13060 | E11: 4030 | F11: =SUM(B11:E11) -> 42320 | G11: 43600 | H11: 30870 | I11: =F11-H11 -> 11450 | J11: =F11/H11 -> 1.3709103
A12: 2026-06-17 | B12: 22630 | C12: 1160 | D12: 6970 | E12: 4030 | F12: =SUM(B12:E12) -> 34790 | G12: 60170 | H12: 14310 | I12: =F12-H12 -> 20480 | J12: =F12/H12 -> 2.431167
A13: 2026-06-19 | B13: 33450 | C13: 1160 | D13: 31670 | E13: 4030 | F13: =SUM(B13:E13) -> 70310 | G13: 4750 | H13: 65140 | I13: =F13-H13 -> 5170 | J13: =F13/H13 -> 1.0793675
A14: 2026-06-22 | B14: 29240 | C14: 2000 | D14: 12300 | E14: 4030 | F14: =SUM(B14:E14) -> 47570 | G14: 40100 | H14: 29780 | I14: =F14-H14 -> 17790 | J14: =F14/H14 -> 1.5973808
A15: 2026-06-24 | B15: 30650 | C15: 350 | D15: 11070 | E15: 2280 | F15: =SUM(B15:E15) -> 44350 | G15: 42940 | H15: 26940 | I15: =F15-H15 -> 17410 | J15: =F15/H15 -> 1.6462509
A16: 2026-06-26 | B16: 26710 | C16: 1200 | D16: 8610 | E16: 2280 | F16: =SUM(B16:E16) -> 38800 | G16: 54280 | H16: 15610 | I16: =F16-H16 -> 23190 | J16: =F16/H16 -> 2.4855862
A17: 2026-06-29 | B17: 33660 | C17: 1500 | D17: 5550 | E17: 2280 | F17: =SUM(B17:E17) -> 42990 | G17: 56340 | H17: 13540 | I17: =F17-H17 -> 29450 | J17: =F17/H17 -> 3.1750369
A20: Notes
A21: • Total Liquidity = bank + cash on hand + receivables not yet settled by processors and delivery platforms.
A22: • Projected Balance = liquidity available after covering all scheduled payables for the period.
A23: • Coverage Ratio = liquidity divided by scheduled payables. Below 1.00 signals a funding gap requiring action.

Sheet Scenario Forecast
A1: SCENARIO FORECAST — VOLUME AND MARGIN MODELING
A2: Six volume scenarios modeling revenue, staffing, cost structure and resulting margin · Illustrative figures
B4: S1 | D4: S2 | F4: S3 | H4: S4 | J4: S5 | L4: S6
A5: VOLUME ASSUMPTIONS
A6: Pizzas per weekend day | B6: 36 | D6: 41 | F6: 45 | H6: 53 | J6: 60 | L6: 110
A7: Pizzas per weekday | B7: 12 | D7: 14 | F7: 15 | H7: 18 | J7: 20 | L7: 37
A8: Total monthly units | B8: =(B6*8)+(B7*22) -> 552 | D8: =(D6*8)+(D7*22) -> 636 | F8: =(F6*8)+(F7*22) -> 690 | H8: =(H6*8)+(H7*22) -> 820 | J8: =(J6*8)+(J7*22) -> 920 | L8: =(L6*8)+(L7*22) -> 1694
A9: Average ticket | B9: 105 | D9: 105 | F9: 105 | H9: 105 | J9: 105 | L9: 105
A10: Kitchen staff (weekend) | B10: 3 | D10: 3 | F10: 4 | H10: 4 | J10: 5 | L10: 7
A11: Kitchen staff (weekday) | B11: 1 | D11: 1 | F11: 1 | H11: 2 | J11: 2 | L11: 2
A13: REVENUE
A14: Total Revenue | B14: =B8*B9 -> 57960 | D14: =D8*D9 -> 66780 | F14: =F8*F9 -> 72450 | H14: =H8*H9 -> 86100 | J14: =J8*J9 -> 96600 | L14: =L8*L9 -> 177870
A15: Sales Taxes | B15: =B14*0.075 -> 4347 | C15: =B15/B14 -> 0.075 | D15: =D14*0.075 -> 5008.5 | E15: =D15/D14 -> 0.075 | F15: =F14*0.075 -> 5433.75 | G15: =F15/F14 -> 0.075 | H15: =H14*0.075 -> 6457.5 | I15: =H15/H14 -> 0.075 | J15: =J14*0.075 -> 7245 | K15: =J15/J14 -> 0.075 | L15: =L14*0.075 -> 13340.25 | M15: =L15/L14 -> 0.075
A16: Platform & Card Fees | B16: =B14*0.05 -> 2898 | C16: =B16/B14 -> 0.05 | D16: =D14*0.05 -> 3339 | E16: =D16/D14 -> 0.05 | F16: =F14*0.05 -> 3622.5 | G16: =F16/F14 -> 0.05 | H16: =H14*0.05 -> 4305 | I16: =H16/H14 -> 0.05 | J16: =J14*0.05 -> 4830 | K16: =J16/J14 -> 0.05 | L16: =L14*0.05 -> 8893.5 | M16: =L16/L14 -> 0.05
A17: Net Operating Revenue | B17: =B14-B15-B16 -> 50715 | C17: =B17/B14 -> 0.875 | D17: =D14-D15-D16 -> 58432.5 | E17: =D17/D14 -> 0.875 | F17: =F14-F15-F16 -> 63393.75 | G17: =F17/F14 -> 0.875 | H17: =H14-H15-H16 -> 75337.5 | I17: =H17/H14 -> 0.875 | J17: =J14-J15-J16 -> 84525 | K17: =J17/J14 -> 0.875 | L17: =L14-L15-L16 -> 155636.25 | M17: =L17/L14 -> 0.875
A19: COST STRUCTURE
A20: Rent | B20: 3260 | C20: =B20/B14 -> 0.056245687 | D20: 3260 | E20: =D20/D14 -> 0.048817011 | F20: 3260 | G20: =F20/F14 -> 0.044996549 | H20: 3460 | I20: =H20/H14 -> 0.04018583 | J20: 3460 | K20: =J20/J14 -> 0.035817805 | L20: 3460 | M20: =L20/L14 -> 0.019452409
A21: Utilities | B21: 930 | C21: =B21/B14 -> 0.016045549 | D21: 930 | E21: =D21/D14 -> 0.013926325 | F21: 830 | G21: =F21/F14 -> 0.011456177 | H21: 990 | I21: =H21/H14 -> 0.011498258 | J21: 990 | K21: =J21/J14 -> 0.010248447 | L21: 990 | M21: =L21/L14 -> 0.0055658627
A22: Payroll | B22: 7500 | C22: =B22/B14 -> 0.12939959 | D22: 7810 | E22: =D22/D14 -> 0.11695118 | F22: 8505 | G22: =F22/F14 -> 0.1173913 | H22: 10500 | I22: =H22/H14 -> 0.12195122 | J22: 10500 | K22: =J22/J14 -> 0.10869565 | L22: 20500 | M22: =L22/L14 -> 0.11525271
A23: Accounting | B23: 680 | C23: =B23/B14 -> 0.011732229 | D23: 680 | E23: =D23/D14 -> 0.010182689 | F23: 680 | G23: =F23/F14 -> 0.0093857833 | H23: 800 | I23: =H23/H14 -> 0.0092915215 | J23: 950 | K23: =J23/J14 -> 0.0098343685 | L23: 950 | M23: =L23/L14 -> 0.0053409794
A24: Insurance & Security | B24: 455 | C24: =B24/B14 -> 0.0078502415 | D24: 405 | E24: =D24/D14 -> 0.00606469 | F24: 405 | G24: =F24/F14 -> 0.0055900621 | H24: 543 | I24: =H24/H14 -> 0.0063066202 | J24: 543 | K24: =J24/J14 -> 0.005621118 | L24: 543 | M24: =L24/L14 -> 0.0030527914
A25: Software & Legal | B25: 535 | C25: =B25/B14 -> 0.0092305038 | D25: 485 | E25: =D25/D14 -> 0.0072626535 | F25: 435 | G25: =F25/F14 -> 0.0060041408 | H25: 743 | I25: =H25/H14 -> 0.0086295006 | J25: 743 | K25: =J25/J14 -> 0.0076915114 | L25: 743 | M25: =L25/L14 -> 0.0041772081
A26: Delivery / Motorbikes | B26: =B14*0.105 -> 6085.8 | C26: =B26/B14 -> 0.105 | D26: =D14*0.105 -> 7011.9 | E26: =D26/D14 -> 0.105 | F26: =F14*0.105 -> 7607.25 | G26: =F26/F14 -> 0.105 | H26: =H14*0.105 -> 9040.5 | I26: =H26/H14 -> 0.105 | J26: =J14*0.105 -> 10143 | K26: =J26/J14 -> 0.105 | L26: =L14*0.105 -> 18676.35 | M26: =L26/L14 -> 0.105
A27: Raw Materials (Food) | B27: =B14*0.35 -> 20286 | C27: =B27/B14 -> 0.35 | D27: =D14*0.35 -> 23373 | E27: =D27/D14 -> 0.35 | F27: =F14*0.35 -> 25357.5 | G27: =F27/F14 -> 0.35 | H27: =H14*0.35 -> 30135 | I27: =H27/H14 -> 0.35 | J27: =J14*0.35 -> 33810 | K27: =J27/J14 -> 0.35 | L27: =L14*0.35 -> 62254.5 | M27: =L27/L14 -> 0.35
A28: Cleaning Supplies | B28: 300 | C28: =B28/B14 -> 0.0051759834 | D28: 300 | E28: =D28/D14 -> 0.004492363 | F28: 250 | G28: =F28/F14 -> 0.0034506556 | H28: 300 | I28: =H28/H14 -> 0.0034843206 | J28: 300 | K28: =J28/J14 -> 0.0031055901 | L28: 300 | M28: =L28/L14 -> 0.0016866251
A29: Owner's Draw | B29: 6000 | C29: =B29/B14 -> 0.10351967 | D29: 7000 | E29: =D29/D14 -> 0.1048218 | F29: 8500 | G29: =F29/F14 -> 0.11732229 | H29: 10000 | I29: =H29/H14 -> 0.11614402 | J29: 12000 | K29: =J29/J14 -> 0.1242236 | L29: 10000 | M29: =L29/L14 -> 0.056220835
A30: Marketing | B30: 2000 | C30: =B30/B14 -> 0.034506556 | D30: 2500 | E30: =D30/D14 -> 0.037436358 | F30: 2000 | G30: =F30/F14 -> 0.027605245 | H30: 2000 | I30: =H30/H14 -> 0.023228804 | J30: 2000 | K30: =J30/J14 -> 0.020703934 | L30: 6000 | M30: =L30/L14 -> 0.033732501
A31: Reinvestment | B31: 500 | C31: =B31/B14 -> 0.0086266391 | D31: 500 | E31: =D31/D14 -> 0.0074872716 | F31: 500 | G31: =F31/F14 -> 0.0069013112 | H31: 500 | I31: =H31/H14 -> 0.0058072009 | J31: 1000 | K31: =J31/J14 -> 0.010351967 | L31: 2000 | M31: =L31/L14 -> 0.011244167
A32: Maintenance | B32: 1000 | C32: =B32/B14 -> 0.017253278 | D32: 500 | E32: =D32/D14 -> 0.0074872716 | F32: 500 | G32: =F32/F14 -> 0.0069013112 | H32: 500 | I32: =H32/H14 -> 0.0058072009 | J32: 1000 | K32: =J32/J14 -> 0.010351967 | L32: 1000 | M32: =L32/L14 -> 0.0056220835
A33: Total Costs | B33: =SUM(B20:B32) -> 49531.8 | C33: =B33/B14 -> 0.85458592 | D33: =SUM(D20:D32) -> 54754.9 | E33: =D33/D14 -> 0.81992962 | F33: =SUM(F20:F32) -> 58829.75 | G33: =F33/F14 -> 0.81200483 | H33: =SUM(H20:H32) -> 69511.5 | I33: =H33/H14 -> 0.80733449 | J33: =SUM(J20:J32) -> 77439 | K33: =J33/J14 -> 0.80164596 | L33: =SUM(L20:L32) -> 127416.85 | M33: =L33/L14 -> 0.71634818
A35: NET PROFIT | B35: =B17-B33 -> 1183.2 | C35: =B35/B14 -> 0.020414079 | D35: =D17-D33 -> 3677.6 | E35: =D35/D14 -> 0.05507038 | F35: =F17-F33 -> 4564 | G35: =F35/F14 -> 0.062995169 | H35: =H17-H33 -> 5826 | I35: =H35/H14 -> 0.067665505 | J35: =J17-J33 -> 7086 | K35: =J35/J14 -> 0.073354037 | L35: =L17-L33 -> 28219.4 | M35: =L35/L14 -> 0.15865182
A36: Total Owner Benefit (profit + draw + reinvestment) | B36: =B35+B29+B31 -> 7683.2 | C36: =B36/B14 -> 0.13256039 | D36: =D35+D29+D31 -> 11177.6 | E36: =D36/D14 -> 0.16737945 | F36: =F35+F29+F31 -> 13564 | G36: =F36/F14 -> 0.18721877 | H36: =H35+H29+H31 -> 16326 | I36: =H36/H14 -> 0.18961672 | J36: =J35+J29+J31 -> 20086 | K36: =J36/J14 -> 0.20792961 | L36: =L35+L29+L31 -> 40219.4 | M36: =L36/L14 -> 0.22611683

Sheet Balance Sheet & Inventory
A1: BALANCE SHEET, INVENTORY & TRUE COGS
A2: Inventory movement drives true COGS · Illustrative figures · Blue = input · Black = formula
B4: Jan | C4: Feb | D4: Mar | E4: Apr | F4: May | G4: Jun
A5: INVENTORY & TRUE COGS
A6: Beginning Inventory | B6: 8200 | C6: 8600 | D6: 8900 | E6: 9100 | F6: 9400 | G6: 9200
A7: Purchases | B7: 10100 | C7: 9750 | D7: 10750 | E7: 11400 | F7: 12200 | G7: 12700
A8: Ending Inventory | B8: 8600 | C8: 8900 | D8: 9100 | E8: 9400 | F8: 9200 | G8: 9600
A9: True COGS (BI + Purchases - EI) | B9: =B6+B7-B8 -> 9700 | C9: =C6+C7-C8 -> 9450 | D9: =D6+D7-D8 -> 10550 | E9: =E6+E7-E8 -> 11100 | F9: =F6+F7-F8 -> 12400 | G9: =G6+G7-G8 -> 12300
A10: Revenue | B10: ='Controller Dashboard'!B9 -> 28500 | C10: ='Controller Dashboard'!C9 -> 27800 | D10: ='Controller Dashboard'!D9 -> 31200 | E10: ='Controller Dashboard'!E9 -> 33500 | F10: ='Controller Dashboard'!F9 -> 35800 | G10: ='Controller Dashboard'!G9 -> 38200
A11: COGS % of Revenue | B11: =B9/B10 -> 0.34035088 | C11: =C9/C10 -> 0.33992806 | D11: =D9/D10 -> 0.33814103 | E11: =E9/E10 -> 0.33134328 | F11: =F9/F10 -> 0.34636872 | G11: =G9/G10 -> 0.32198953
A12: MoM COGS % change | C12: =C11-B11 -> -0.00042281964 | D12: =D11-C11 -> -0.0017870319 | E12: =E11-D11 -> -0.0067977421 | F12: =F11-E11 -> 0.015025432 | G12: =G11-F11 -> -0.024379186
A14: CASH & CAPITAL POSITION
A15: Bank Account | B15: 24500 | C15: 26800 | D15: 28100 | E15: 27400 | F15: 29900 | G15: 31200
A16: Cash on Hand | B16: 800 | C16: 750 | D16: 900 | E16: 850 | F16: 1100 | G16: 1000
A17: Processor Receivable | B17: 12400 | C17: 13100 | D17: 14200 | E17: 13800 | F17: 15100 | G17: 15600
A18: Delivery Receivable | B18: 3900 | C18: 4100 | D18: 4400 | E18: 4200 | F18: 4600 | G18: 4800
A19: Total Receivables | B19: =B17+B18 -> 16300 | C19: =C17+C18 -> 17200 | D19: =D17+D18 -> 18600 | E19: =E17+E18 -> 18000 | F19: =F17+F18 -> 19700 | G19: =G17+G18 -> 20400
A20: Inventory (asset) | B20: =B8 -> 8600 | C20: =C8 -> 8900 | D20: =D8 -> 9100 | E20: =E8 -> 9400 | F20: =F8 -> 9200 | G20: =G8 -> 9600
A21: Raw Material Payables | B21: 6800 | C21: 7100 | D21: 7300 | E21: 7000 | F21: 7600 | G21: 7900
A22: Net Capital Position | B22: =B15+B16+B19+B20-B21 -> 43400 | C22: =C15+C16+C19+C20-C21 -> 46550 | D22: =D15+D16+D19+D20-D21 -> 49400 | E22: =E15+E16+E19+E20-E21 -> 48650 | F22: =F15+F16+F19+F20-F21 -> 52300 | G22: =G15+G16+G19+G20-G21 -> 54300
A23: MoM Capital Change | C23: =C22-B22 -> 3150 | D23: =D22-C22 -> 2850 | E23: =E22-D22 -> -750 | F23: =F22-E22 -> 3650 | G23: =G22-F22 -> 2000
A25: REVENUE BY CUSTOMER TYPE
A26: Total Customers Served | B26: 286 | C26: 301 | D26: 318 | E26: 332 | F26: 349 | G26: 358
A27: Recurring Customers | B27: 198 | C27: 215 | D27: 232 | E27: 248 | F27: 264 | G27: 275
A28: Recurring Customer Share | B28: =B27/B26 -> 0.69230769 | C28: =C27/C26 -> 0.71428571 | D28: =D27/D26 -> 0.72955975 | E28: =E27/E26 -> 0.74698795 | F28: =F27/F26 -> 0.75644699 | G28: =G27/G26 -> 0.76815642
A29: New Customers | B29: =B26-B27 -> 88 | C29: =C26-C27 -> 86 | D29: =D26-D27 -> 86 | E29: =E26-E27 -> 84 | F29: =F26-F27 -> 85 | G29: =G26-G27 -> 83
A30: Revenue from Recurring | B30: =B10*B28 -> 19730.769 | C30: =C10*C28 -> 19857.143 | D30: =D10*D28 -> 22762.264 | E30: =E10*E28 -> 25024.096 | F30: =F10*F28 -> 27080.802 | G30: =G10*G28 -> 29343.575
A31: Revenue from New | B31: =B10-B30 -> 8769.2308 | C31: =C10-C30 -> 7942.8571 | D31: =D10-D30 -> 8437.7358 | E31: =E10-E30 -> 8475.9036 | F31: =F10-F30 -> 8719.1977 | G31: =G10-G30 -> 8856.4246
A32: Average Order Value | B32: =B10/B26 -> 99.65035 | C32: =C10/C26 -> 92.358804 | D32: =D10/D26 -> 98.113208 | E32: =E10/E26 -> 100.90361 | F32: =F10/F26 -> 102.5788 | G32: =G10/G26 -> 106.70391

Sheet Menu Pricing
A1: MENU PRICING & MARGIN MODEL
A2: Cost-driven pricing by item and size, with target margin · Illustrative figures
A4: Menu Item | B4: Small Cost | C4: Large Cost | D4: XL Cost | E4: Target Margin | F4: Small Price | G4: Large Price | H4: XL Price | I4: Small GM% | J4: Large GM% | K4: XL GM%
A5: Margherita | B5: 7.2 | C5: 10.8 | D5: 13.4 | E5: 0.68 | F5: =ROUND(B5/(1-$E5),0) -> 23 | G5: =ROUND(C5/(1-$E5),0) -> 34 | H5: =ROUND(D5/(1-$E5),0) -> 42 | I5: =(F5-B5)/F5 -> 0.68695652 | J5: =(G5-C5)/G5 -> 0.68235294 | K5: =(H5-D5)/H5 -> 0.68095238
A6: Pepperoni | B6: 8.1 | C6: 12.2 | D6: 15.1 | E6: 0.68 | F6: =ROUND(B6/(1-$E6),0) -> 25 | G6: =ROUND(C6/(1-$E6),0) -> 38 | H6: =ROUND(D6/(1-$E6),0) -> 47 | I6: =(F6-B6)/F6 -> 0.676 | J6: =(G6-C6)/G6 -> 0.67894737 | K6: =(H6-D6)/H6 -> 0.6787234
A7: Four Cheese | B7: 9.4 | C7: 13.6 | D7: 16.8 | E7: 0.68 | F7: =ROUND(B7/(1-$E7),0) -> 29 | G7: =ROUND(C7/(1-$E7),0) -> 43 | H7: =ROUND(D7/(1-$E7),0) -> 53 | I7: =(F7-B7)/F7 -> 0.67586207 | J7: =(G7-C7)/G7 -> 0.68372093 | K7: =(H7-D7)/H7 -> 0.68301887
A8: Chicken & Cream Cheese | B8: 8.6 | C8: 12.9 | D8: 15.9 | E8: 0.68 | F8: =ROUND(B8/(1-$E8),0) -> 27 | G8: =ROUND(C8/(1-$E8),0) -> 40 | H8: =ROUND(D8/(1-$E8),0) -> 50 | I8: =(F8-B8)/F8 -> 0.68148148 | J8: =(G8-C8)/G8 -> 0.6775 | K8: =(H8-D8)/H8 -> 0.682
A9: Portuguesa | B9: 7.9 | C9: 11.8 | D9: 14.6 | E9: 0.68 | F9: =ROUND(B9/(1-$E9),0) -> 25 | G9: =ROUND(C9/(1-$E9),0) -> 37 | H9: =ROUND(D9/(1-$E9),0) -> 46 | I9: =(F9-B9)/F9 -> 0.684 | J9: =(G9-C9)/G9 -> 0.68108108 | K9: =(H9-D9)/H9 -> 0.6826087
A10: Beef & Onion | B10: 8.8 | C10: 13.1 | D10: 16.2 | E10: 0.68 | F10: =ROUND(B10/(1-$E10),0) -> 28 | G10: =ROUND(C10/(1-$E10),0) -> 41 | H10: =ROUND(D10/(1-$E10),0) -> 51 | I10: =(F10-B10)/F10 -> 0.68571429 | J10: =(G10-C10)/G10 -> 0.6804878 | K10: =(H10-D10)/H10 -> 0.68235294
A11: Broccoli & Bacon | B11: 8.3 | C11: 12.4 | D11: 15.3 | E11: 0.68 | F11: =ROUND(B11/(1-$E11),0) -> 26 | G11: =ROUND(C11/(1-$E11),0) -> 39 | H11: =ROUND(D11/(1-$E11),0) -> 48 | I11: =(F11-B11)/F11 -> 0.68076923 | J11: =(G11-C11)/G11 -> 0.68205128 | K11: =(H11-D11)/H11 -> 0.68125
A12: Ham & Olives | B12: 7.6 | C12: 11.4 | D12: 14.1 | E12: 0.68 | F12: =ROUND(B12/(1-$E12),0) -> 24 | G12: =ROUND(C12/(1-$E12),0) -> 36 | H12: =ROUND(D12/(1-$E12),0) -> 44 | I12: =(F12-B12)/F12 -> 0.68333333 | J12: =(G12-C12)/G12 -> 0.68333333 | K12: =(H12-D12)/H12 -> 0.67954545
A13: Banana & Cinnamon (dessert) | B13: 5.4 | C13: 8.1 | D13: 10 | E13: 0.68 | F13: =ROUND(B13/(1-$E13),0) -> 17 | G13: =ROUND(C13/(1-$E13),0) -> 25 | H13: =ROUND(D13/(1-$E13),0) -> 31 | I13: =(F13-B13)/F13 -> 0.68235294 | J13: =(G13-C13)/G13 -> 0.676 | K13: =(H13-D13)/H13 -> 0.67741935
A14: Dark Chocolate (dessert) | B14: 6.2 | C14: 9.3 | D14: 11.5 | E14: 0.68 | F14: =ROUND(B14/(1-$E14),0) -> 19 | G14: =ROUND(C14/(1-$E14),0) -> 29 | H14: =ROUND(D14/(1-$E14),0) -> 36 | I14: =(F14-B14)/F14 -> 0.67368421 | J14: =(G14-C14)/G14 -> 0.67931034 | K14: =(H14-D14)/H14 -> 0.68055556
A17: Notes
A18: • Price is derived from ingredient cost and the target gross margin: Price = Cost / (1 - Target Margin).
A19: • When ingredient costs change in the inventory sheet, prices and margins update automatically.
A20: • Target margin is set per item, allowing higher-margin items to subsidize traffic drivers.
